BrosHelp/BrosHelp.py
BrosHelp/Start.py
BrosHelp/__init__.py
BrosHelp/__main__.py
BrosHelps-0.1.1.dist-info/DESCRIPTION.rst
BrosHelps-0.1.1.dist-info/METADATA
BrosHelps-0.1.1.dist-info/RECORD
BrosHelps-0.1.1.dist-info/WHEEL
BrosHelps-0.1.1.dist-info/entry_points.txt
BrosHelps-0.1.1.dist-info/metadata.json
BrosHelps-0.1.1.dist-info/top_level.txt
