Metadata-Version: 2.0
Name: BrosHelps
Version: 0.1.1
Summary: BrosHelp Bot
Home-page: https://github.com/KayShenA/PythonProjects
Author: Kay
Author-email: skyluckyrrb@126.com
License: MIT
Platform: any
